dependency_check.py
dependency_check-0.6.0.dist-info/LICENSE
dependency_check-0.6.0.dist-info/METADATA
dependency_check-0.6.0.dist-info/WHEEL
dependency_check-0.6.0.dist-info/entry_points.txt
dependency_check-0.6.0.dist-info/top_level.txt
dependency_check-0.6.0.dist-info/RECORD
