Metadata-Version: 2.1
Name: dependency-check
Version: 0.6.0
Summary: Shim to easily install OWASP dependency-check-cli into Python projects
Home-page: https://github.com/jhermann/dependency-check-py
Author: Jürgen Hermann
Author-email: jh@web.de
License: Apache 2.0
Keywords: owasp,security,vulnerability,quality-assurance
Platform: UNKNOWN
Classifier: Development Status :: 5 - Production/Stable
Classifier: Programming Language :: Python
Classifier: Programming Language :: Python :: 2
Classifier: Programming Language :: Python :: 2.7
Classifier: Programming Language :: Python :: 3
Classifier: Programming Language :: Python :: 3.4
Classifier: Environment :: Console
Classifier: Intended Audience :: Developers
Classifier: Intended Audience :: Information Technology
Classifier: Intended Audience :: System Administrators
Classifier: License :: OSI Approved :: Apache Software License
Classifier: Operating System :: OS Independent
Classifier: Topic :: Security
Classifier: Topic :: Software Development :: Quality Assurance
Classifier: Topic :: Utilities
